consoleverse/__init__.py
consoleverse/clear.py
consoleverse/console.py
consoleverse/input.py
consoleverse/styling.py
consoleverse/utils.py
consoleverse/config/__init__.py
consoleverse/config/lang.py
consoleverse/config/settings.py
consoleverse/config/themes.py
consoleverse/exceptions/__init__.py
consoleverse/exceptions/ex_console.py
consoleverse/term/__init__.py
consoleverse/term/color_style.py
consoleverse/term/emojis.py
consoleverse/term/exceptions/__init__.py
consoleverse/term/exceptions/ex_colors.py
tests/__init__.py
tests/test_clear.py
tests/test_input.py
tests/test_styling.py
tests/test_utils.py
tests/console/__init__.py
tests/console/test_console_println.py
ConsoleVerse-0.1.0.dist-info/LICENSE
ConsoleVerse-0.1.0.dist-info/METADATA
ConsoleVerse-0.1.0.dist-info/WHEEL
ConsoleVerse-0.1.0.dist-info/top_level.txt
ConsoleVerse-0.1.0.dist-info/RECORD
