Metadata-Version: 2.1
Name: ConsoleVerse
Version: 0.1.0
Summary: A Python library for managing console output.
Home-page: https://github.com/JuanS3/consoleverse
Author: Sebastian Martinez
Author-email: Sebastian Martinez <sebastian.martinez.serna@gmail.com>
Project-URL: Homepage, https://github.com/JuanS3/ConsoleVerse
Project-URL: Issues, https://github.com/JuanS3/ConsoleVerse/issues
Classifier: Programming Language :: Python :: 3
Classifier: License :: OSI Approved :: MIT License
Classifier: Operating System :: OS Independent
Classifier: Development Status :: 4 - Beta
Classifier: Environment :: Console
Requires-Python: >=3.8
License-File: LICENSE
